{"name":"Vruivtk","tagline":"Application demonstrating the use of vtkRenderingExternal module to render VTK objects in the VRUI context","body":"### Welcome to VruiVTK\r\nThis application demonstrates use of the new vtkRenderingExternal module for VRUI and VTK integration.\r\n\r\n### Supported Operating Systems\r\n* Linux\r\n* Mac OSX\r\n\r\n### Prerequisites\r\nNOTE: To build VruiVTK along with all its prerequisites, simply build the superbuild from [VruiVTKSuperbuild](https://github.com/vruivtk/Vruivtksuperbuild)\r\n\r\nVruiVTK application requires the following software to be built and installed.\r\n* [CMake](http://cmake.org)\r\n* [Vrui](http://idav.ucdavis.edu/~okreylos/ResDev/Vrui/)\r\n* [VTK with the vtkRenderingExternal module turned ON](https://github.com/sankhesh/VTK/tree/Rendering_External_Module)\r\n* [TCLAP](http://tclap.sourceforge.net/) \r\n\r\n### Clone VruiVTK source\r\nThe VruiVTK application can be built from source obtained using one of the download links on this page or using the commandline as follows:\r\n\r\n``\r\n$ git clone https://github.com/VruiVTK/VruiVTK.git\r\n``\r\n\r\nThe above command creates a directory _VruiVTK_ with the source code.\r\n\r\n### Configure Instructions\r\nConfigure the build using CMake.\r\n\r\nSet the following CMake variables:\r\n```\r\n* VRUI_PKGCONFIG - Path to pkgconfig directory of your VRUI installation\r\n* VTK_DIR - Path to the VTK build directory\r\n* TCLAP_INCLUDE_DIR - Path to include directory of your TCLAP installation\r\n```\r\n\r\nOnce all the required variables are set, press `generate` to generate the makefile.\r\n\r\n### Build Instructions\r\nBuild using the make tool.\r\n\r\n```\r\n$ make\r\n```\r\n\r\n### Run VruiVTK\r\nThe build step will create an executable _VruiVTK_ under the build directory that can be used to run the application.\r\nTo get usage instructions for the application:\r\n\r\n```\r\n$ VruiVTK --help\r\n```\r\nTo render an OBJ file using VTK, use the '-f' or '--fileName' argument.\r\n```\r\n$ VruiVTK -f cow-nonormals.obj\r\n```\r\nThe following image shows VTK rendering an OBJ dataset in the VRUI context. The dataset was obtained from [here](http://groups.csail.mit.edu/graphics/classes/6.837/F03/models/cow-nonormals.obj).\r\n![VruiVTK with VTK Cow OBJ](https://drive.google.com/file/d/0Bxgq5zla1NcFVVpIckZ5TF8tTjA/edit?usp=sharing)\r\n\r\nIf no arguments are provided, the application will bring up a VRUI window with a vtkCube rendered at its origin.\r\n![VruiVTK with vtkCube](https://drive.google.com/file/d/0Bxgq5zla1NcFaWtGTzRoZEg4SHc/edit?usp=sharing)","google":"","note":"Don't delete this file! It's used internally to help with page regeneration."}